foliant/preprocessors/multilinetables.py
foliantcontrib.multilinetables-1.2.3.dist-info/LICENSE
foliantcontrib.multilinetables-1.2.3.dist-info/METADATA
foliantcontrib.multilinetables-1.2.3.dist-info/WHEEL
foliantcontrib.multilinetables-1.2.3.dist-info/top_level.txt
foliantcontrib.multilinetables-1.2.3.dist-info/RECORD
