Metadata-Version: 2.1
Name: foliantcontrib.multilinetables
Version: 1.2.3
Summary: Markdown tables convertor to a multiline and grid format.
Home-page: https://github.com/foliant-docs/foliantcontrib.multilinetables
Author: Anton Bukhtiyarov
Author-email: apkraft@gmail.com
License: MIT
Platform: any
Classifier: Development Status :: 5 - Production/Stable
Classifier: Environment :: Console
Classifier: Intended Audience :: Developers
Classifier: License :: OSI Approved :: MIT License
Classifier: Operating System :: OS Independent
Classifier: Programming Language :: Python
Classifier: Topic :: Documentation
Classifier: Topic :: Utilities
Requires-Dist: foliant (>=1.0.5)
